SansiLibrary/CommonKeywords.py
SansiLibrary/RequestsSessionKeywords.py
SansiLibrary/StarRiverKeywords.py
SansiLibrary/__init__.py
SansiLibrary/commonDecorator.py
SansiLibrary/version.py
SansiLibrary-0.0.8.dist-info/METADATA
SansiLibrary-0.0.8.dist-info/WHEEL
SansiLibrary-0.0.8.dist-info/top_level.txt
SansiLibrary-0.0.8.dist-info/RECORD
