Metadata-Version: 2.1
Name: SansiLibrary
Version: 0.0.8
Summary: San si Robotframework library
Author: maoyongfan
Author-email: maoyongfan@163.com
License: MIT
Keywords: api test python language frameworks
Classifier: Development Status :: 3 - Alpha
Classifier: Intended Audience :: Developers
Classifier: Topic :: Software Development :: Build Tools
Classifier: License :: OSI Approved :: MIT License
Classifier: Programming Language :: Python :: 3
Classifier: Programming Language :: Python :: 3.6
Classifier: Operating System :: OS Independent
Requires-Python: >=3
Requires-Dist: robotframework
